dare/__init__.py
dare/_argsort.c
dare/_argsort.cp38-win32.pyd
dare/_classes.py
dare/_config.c
dare/_config.cp38-win32.pyd
dare/_manager.c
dare/_manager.cp38-win32.pyd
dare/_remover.c
dare/_remover.cp38-win32.pyd
dare/_simulator.c
dare/_simulator.cp38-win32.pyd
dare/_splitter.c
dare/_splitter.cp38-win32.pyd
dare/_tree.c
dare/_tree.cp38-win32.pyd
dare/_utils.c
dare/_utils.cp38-win32.pyd
dare/setup.py
dare_rf-1.1.4.dist-info/LICENSE
dare_rf-1.1.4.dist-info/METADATA
dare_rf-1.1.4.dist-info/WHEEL
dare_rf-1.1.4.dist-info/top_level.txt
dare_rf-1.1.4.dist-info/RECORD
