Metadata-Version: 2.1
Name: dare-rf
Version: 1.1.4
Summary: Data Removal-Enabled Random Forests
Home-page: https://github.com/jjbrophy47/dare
Author: Jonathan Brophy
Author-email: jbrophy@cs.uoregon.edu
Classifier: Programming Language :: Python :: 3.7
Classifier: Programming Language :: Python :: 3.8
Classifier: Programming Language :: Python :: 3.9
Classifier: Programming Language :: Python :: 3.10
Classifier: License :: OSI Approved :: Apache Software License
Classifier: Operating System :: OS Independent
Requires-Python: >=3.7
License-File: LICENSE
Requires-Dist: numpy >=1.22
